Workbook

Sheet Productos
A1: ID Producto | B1: Nombre del Producto | C1: Categoría | D1: Precio (MXN) | E1: Cantidad | F1: Talla / Medida | G1: Color | H1: Marca | I1: Descripción | J1: URL Foto | K1: URL Video | L1: Condición | M1: Estado | N1: Disponibilidad Automática | O1: Fecha de Alta | P1: Destacado | Q1: Publicado en WhatsApp | R1: Enlace WhatsApp
A2: P001 | B2: Tenis Nike Air Max 90 | C2: Calzado | D2: 1650 | E2: 1 | F2: 26 MX (8 US) | G2: Negro | H2: Nike | I2: Tenis originales en caja, talla 26 MX (8 US) | J2: https://images.unsplash.com/photo-1542291026-7eec264c27ff?w=800 | K2: https://ejemplo.com/videos/p001.mp4 | L2: Nuevo | M2: Disponible | N2: =IF(A2="","",IF(M2="Oculto","Oculto",IF(M2="Apartado","Apartado",IF(OR(E2<=0,M2="Vendido"),"Agotado","Disponible")))) | O2: 2026-10-30 | P2: Sí | Q2: Sí | R2: =IF(B2="","","https://wa.me/"&Dashboard!$C$6&"?text=Hola%2C%20me%20interesa%20comprar%20"&SUBSTITUTE(TRIM(B2)," ","%20")&"%20(ID%3A%20"&A2&"%20-%20%24"&TEXT(D2,"#,##0")&"%20MXN)")
A3: P002 | B3: Chamarra Mezclilla Dama | C3: Ropa de Mujer | D3: 450 | E3: 3 | F3: Mediana | G3: Azul | H3: Importada | I3: Chamarra de mezclilla importada corte clásico | J3: https://images.unsplash.com/photo-1551537482-f2075a1d41f2?w=800 | K3: https://ejemplo.com/videos/p002.mp4 | L3: Nuevo | M3: Disponible | N3: =IF(A3="","",IF(M3="Oculto","Oculto",IF(M3="Apartado","Apartado",IF(OR(E3<=0,M3="Vendido"),"Agotado","Disponible")))) | O3: 2026-10-30 | P3: Sí | Q3: No | R3: =IF(B3="","","https://wa.me/"&Dashboard!$C$6&"?text=Hola%2C%20me%20interesa%20comprar%20"&SUBSTITUTE(TRIM(B3)," ","%20")&"%20(ID%3A%20"&A3&"%20-%20%24"&TEXT(D3,"#,##0")&"%20MXN)")
A4: P003 | B4: Set Labiales Matte Larga Duración | C4: Belleza | D4: 280 | E4: 5 | F4: Estándar | G4: Tonos Nude | H4: MAC Style | I4: Kit de 4 labiales líquidos indelebles larga duración | J4: https://images.unsplash.com/photo-1586495777744-4413f21062fa?w=800 | K4: https://ejemplo.com/videos/p003.mp4 | L4: Nuevo | M4: Disponible | N4: =IF(A4="","",IF(M4="Oculto","Oculto",IF(M4="Apartado","Apartado",IF(OR(E4<=0,M4="Vendido"),"Agotado","Disponible")))) | O4: 2026-10-30 | P4: No | Q4: Sí | R4: =IF(B4="","","https://wa.me/"&Dashboard!$C$6&"?text=Hola%2C%20me%20interesa%20comprar%20"&SUBSTITUTE(TRIM(B4)," ","%20")&"%20(ID%3A%20"&A4&"%20-%20%24"&TEXT(D4,"#,##0")&"%20MXN)")
A5: P004 | B5: Audífonos Inalámbricos Bluetooth Pro | C5: Electrónica | D5: 520 | E5: 1 | F5: Única | G5: Blanco | H5: TechPro | I5: Cancelación de ruido activa y estuche de carga rápida | J5: https://images.unsplash.com/photo-1505740420928-5e560c06d30e?w=800 | K5: https://ejemplo.com/videos/p004.mp4 | L5: Nuevo | M5: Apartado | N5: =IF(A5="","",IF(M5="Oculto","Oculto",IF(M5="Apartado","Apartado",IF(OR(E5<=0,M5="Vendido"),"Agotado","Disponible")))) | O5: 2026-10-29 | P5: Sí | Q5: Sí | R5: =IF(B5="","","https://wa.me/"&Dashboard!$C$6&"?text=Hola%2C%20me%20interesa%20comprar%20"&SUBSTITUTE(TRIM(B5)," ","%20")&"%20(ID%3A%20"&A5&"%20-%20%24"&TEXT(D5,"#,##0")&"%20MXN)")
A6: P005 | B6: Bolsa Crossbody Piel Sintética | C6: Bolsas y Mochilas | D6: 390 | E6: 2 | F6: Chica | G6: Camel | H6: Guess Style | I6: Bolsa cruzada con correa ajustable y herrajes dorados | J6: https://images.unsplash.com/photo-1548036328-c9fa89d128fa?w=800 | K6: https://ejemplo.com/videos/p005.mp4 | L6: Nuevo | M6: Disponible | N6: =IF(A6="","",IF(M6="Oculto","Oculto",IF(M6="Apartado","Apartado",IF(OR(E6<=0,M6="Vendido"),"Agotado","Disponible")))) | O6: 2026-10-29 | P6: No | Q6: No | R6: =IF(B6="","","https://wa.me/"&Dashboard!$C$6&"?text=Hola%2C%20me%20interesa%20comprar%20"&SUBSTITUTE(TRIM(B6)," ","%20")&"%20(ID%3A%20"&A6&"%20-%20%24"&TEXT(D6,"#,##0")&"%20MXN)")
A7: P006 | B7: Sudadera Oversize Caballero | C7: Ropa de Hombre | D7: 480 | E7: 0 | F7: Grande | G7: Gris Oxford | H7: Champion | I7: Sudadera afelpada original talla G, agotada en primer lote | J7: https://images.unsplash.com/photo-1556821840-3a63f95609a7?w=800 | K7: https://ejemplo.com/videos/p006.mp4 | L7: Nuevo | M7: Vendido | N7: =IF(A7="","",IF(M7="Oculto","Oculto",IF(M7="Apartado","Apartado",IF(OR(E7<=0,M7="Vendido"),"Agotado","Disponible")))) | O7: 2026-10-28 | P7: No | Q7: Sí | R7: =IF(B7="","","https://wa.me/"&Dashboard!$C$6&"?text=Hola%2C%20me%20interesa%20comprar%20"&SUBSTITUTE(TRIM(B7)," ","%20")&"%20(ID%3A%20"&A7&"%20-%20%24"&TEXT(D7,"#,##0")&"%20MXN)")
A8: P007 | B8: Caja Gomitas Enchiladas Importadas | C8: Dulces y Botanas | D8: 185 | E8: 8 | F8: 500 g | G8: Surtido | H8: Chamoy Mix | I8: Paquete sellado de gomitas dulces con chile y chamoy | J8: https://images.unsplash.com/photo-1582058091505-f87a2e55a40f?w=800 | K8: https://ejemplo.com/videos/p007.mp4 | L8: Nuevo | M8: Disponible | N8: =IF(A8="","",IF(M8="Oculto","Oculto",IF(M8="Apartado","Apartado",IF(OR(E8<=0,M8="Vendido"),"Agotado","Disponible")))) | O8: 2026-10-30 | P8: No | Q8: No | R8: =IF(B8="","","https://wa.me/"&Dashboard!$C$6&"?text=Hola%2C%20me%20interesa%20comprar%20"&SUBSTITUTE(TRIM(B8)," ","%20")&"%20(ID%3A%20"&A8&"%20-%20%24"&TEXT(D8,"#,##0")&"%20MXN)")
A9: P008 | B9: Reloj Minimalista Acero Inoxidable | C9: Accesorios | D9: 590 | E9: 2 | F9: Ajustable | G9: Dorado / Negro | H9: Casio | I9: Resistente al agua, extensible metálico, incluye estuche | J9: https://images.unsplash.com/photo-1524592094714-0f0654e20314?w=800 | K9: https://ejemplo.com/videos/p008.mp4 | L9: Nuevo | M9: Disponible | N9: =IF(A9="","",IF(M9="Oculto","Oculto",IF(M9="Apartado","Apartado",IF(OR(E9<=0,M9="Vendido"),"Agotado","Disponible")))) | O9: 2026-10-30 | P9: Sí | Q9: No | R9: =IF(B9="","","https://wa.me/"&Dashboard!$C$6&"?text=Hola%2C%20me%20interesa%20comprar%20"&SUBSTITUTE(TRIM(B9)," ","%20")&"%20(ID%3A%20"&A9&"%20-%20%24"&TEXT(D9,"#,##0")&"%20MXN)")

Sheet Clientes
A1: ID Cliente | B1: Nombre(s) | C1: Apellidos | D1: Nombre Completo | E1: Teléfono | F1: WhatsApp | G1: Chat Directo WhatsApp | H1: Correo Electrónico | I1: Categorías de Interés | J1: Fecha de Registro | K1: Último Pedido | L1: Total de Pedidos | M1: Total Comprado (MXN) | N1: Estado
A2: C001 | B2: María | C2: López García | D2: =IF(AND(B2="",C2=""),"",TRIM(B2&" "&C2)) | E2: 5512345678 | F2: 525512345678 | G2: =IF(F2="","","https://wa.me/"&SUBSTITUTE(F2," ","")) | H2: maria.lopez@gmail.com | I2: Calzado, Belleza, Ropa de Mujer | J2: 2026-10-15 | K2: 2026-10-29 | L2: =IF(A2="","",COUNTIF(Pedidos!$C$2:$C$500,A2)) | M2: =IF(A2="","",SUMIFS(Pedidos!$J$2:$J$500,Pedidos!$C$2:$C$500,A2,Pedidos!$M$2:$M$500,"Aprobado")) | N2: VIP
A3: C002 | B3: Carlos | C3: Hernández Ruiz | D3: =IF(AND(B3="",C3=""),"",TRIM(B3&" "&C3)) | E3: 5587654321 | F3: 525587654321 | G3: =IF(F3="","","https://wa.me/"&SUBSTITUTE(F3," ","")) | H3: carlos.hdz@hotmail.com | I3: Ropa de Hombre, Electrónica | J3: 2026-10-20 | K3: 2026-10-30 | L3: =IF(A3="","",COUNTIF(Pedidos!$C$2:$C$500,A3)) | M3: =IF(A3="","",SUMIFS(Pedidos!$J$2:$J$500,Pedidos!$C$2:$C$500,A3,Pedidos!$M$2:$M$500,"Aprobado")) | N3: Activo
A4: C003 | B4: Fernanda | C4: Martínez Soto | D4: =IF(AND(B4="",C4=""),"",TRIM(B4&" "&C4)) | E4: 7223456789 | F4: 527223456789 | G4: =IF(F4="","","https://wa.me/"&SUBSTITUTE(F4," ","")) | H4: fer.mtz@gmail.com | I4: Bolsas y Mochilas, Ropa de Mujer | J4: 2026-10-24 | K4: 2026-10-30 | L4: =IF(A4="","",COUNTIF(Pedidos!$C$2:$C$500,A4)) | M4: =IF(A4="","",SUMIFS(Pedidos!$J$2:$J$500,Pedidos!$C$2:$C$500,A4,Pedidos!$M$2:$M$500,"Aprobado")) | N4: Activo
A5: C004 | B5: Alejandro | C5: Gómez Pérez | D5: =IF(AND(B5="",C5=""),"",TRIM(B5&" "&C5)) | E5: 7229876543 | F5: 527229876543 | G5: =IF(F5="","","https://wa.me/"&SUBSTITUTE(F5," ","")) | H5: alex.gomez@yahoo.com | I5: Calzado, Accesorios | J5: 2026-10-28 | L5: =IF(A5="","",COUNTIF(Pedidos!$C$2:$C$500,A5)) | M5: =IF(A5="","",SUMIFS(Pedidos!$J$2:$J$500,Pedidos!$C$2:$C$500,A5,Pedidos!$M$2:$M$500,"Aprobado")) | N5: Activo
A6: C005 | B6: Valeria | C6: Ramírez Cruz | D6: =IF(AND(B6="",C6=""),"",TRIM(B6&" "&C6)) | E6: 5544332211 | F6: 525544332211 | G6: =IF(F6="","","https://wa.me/"&SUBSTITUTE(F6," ","")) | H6: vale.ramirez@gmail.com | I6: Dulces y Botanas, Belleza | J6: 2026-10-30 | L6: =IF(A6="","",COUNTIF(Pedidos!$C$2:$C$500,A6)) | M6: =IF(A6="","",SUMIFS(Pedidos!$J$2:$J$500,Pedidos!$C$2:$C$500,A6,Pedidos!$M$2:$M$500,"Aprobado")) | N6: Activo

Sheet Pedidos
A1: ID Pedido | B1: Fecha | C1: ID Cliente | D1: Nombre del Cliente | E1: Teléfono | F1: ID Producto | G1: Nombre del Producto | H1: Cantidad | I1: Precio Unitario (MXN) | J1: Total del Pedido (MXN) | K1: Método de Pago | L1: URL Comprobante | M1: Estado de Pago | N1: Estado del Pedido | O1: Notas
A2: PED-001 | B2: 2026-10-28 | C2: C002 | D2: Carlos Hernández Ruiz | E2: 5587654321 | F2: P006 | G2: Sudadera Oversize Caballero | H2: 1 | I2: 480 | J2: =IF(OR(H2="",I2=""),"",H2*I2) | K2: Transferencia SPEI | L2: /uploads/comprobante_ped001.png | M2: Aprobado | N2: Entregado | O2: Pago verificado y entregado en punto acordado
A3: PED-002 | B3: 2026-10-29 | C3: C001 | D3: María López García | E3: 5512345678 | F3: P003 | G3: Set Labiales Matte Larga Duración | H3: 2 | I3: 280 | J3: =IF(OR(H3="",I3=""),"",H3*I3) | K3: Depósito OXXO | L3: /uploads/comprobante_ped002.png | M3: Aprobado | N3: Listo para Entrega | O3: Ticket OXXO confirmado, pasa a recoger
A4: PED-003 | B4: 2026-10-30 | C4: C002 | D4: Carlos Hernández Ruiz | E4: 5587654321 | F4: P004 | G4: Audífonos Inalámbricos Bluetooth Pro | H4: 1 | I4: 520 | J4: =IF(OR(H4="",I4=""),"",H4*I4) | K4: Transferencia SPEI | L4: /uploads/comprobante_ped003.png | M4: Pendiente | N4: Apartado | O4: Esperando validación de captura SPEI
A5: PED-004 | B5: 2026-10-30 | C5: C003 | D5: Fernanda Martínez Soto | E5: 7223456789 | F5: P002 | G5: Chamarra Mezclilla Dama | H5: 1 | I5: 450 | J5: =IF(OR(H5="",I5=""),"",H5*I5) | K5: Transferencia SPEI | L5: /uploads/comprobante_ped004.png | M5: Aprobado | N5: Pagado | O5: Transferencia confirmada, preparar paquete

Sheet Categorías
A1: ID Categoría | B1: Nombre de Categoría | C1: URL Imagen | D1: Activa | E1: Productos Registrados | F1: Unidades Disponibles
A2: CAT001 | B2: Ropa de Mujer | C2: https://images.unsplash.com/photo-1483985988355-763728e1935b?w=800 | D2: Sí | E2: =IF(B2="","",COUNTIF(Productos!$C$2:$C$500,B2)) | F2: =IF(B2="","",SUMIFS(Productos!$E$2:$E$500,Productos!$C$2:$C$500,B2,Productos!$N$2:$N$500,"Disponible"))
A3: CAT002 | B3: Ropa de Hombre | C3: https://images.unsplash.com/photo-1490578474895-699cd4e2cf59?w=800 | D3: Sí | E3: =IF(B3="","",COUNTIF(Productos!$C$2:$C$500,B3)) | F3: =IF(B3="","",SUMIFS(Productos!$E$2:$E$500,Productos!$C$2:$C$500,B3,Productos!$N$2:$N$500,"Disponible"))
A4: CAT003 | B4: Calzado | C4: https://images.unsplash.com/photo-1542291026-7eec264c27ff?w=800 | D4: Sí | E4: =IF(B4="","",COUNTIF(Productos!$C$2:$C$500,B4)) | F4: =IF(B4="","",SUMIFS(Productos!$E$2:$E$500,Productos!$C$2:$C$500,B4,Productos!$N$2:$N$500,"Disponible"))
A5: CAT004 | B5: Belleza | C5: https://images.unsplash.com/photo-1596462502278-27bfdc403348?w=800 | D5: Sí | E5: =IF(B5="","",COUNTIF(Productos!$C$2:$C$500,B5)) | F5: =IF(B5="","",SUMIFS(Productos!$E$2:$E$500,Productos!$C$2:$C$500,B5,Productos!$N$2:$N$500,"Disponible"))
A6: CAT005 | B6: Electrónica | C6: https://images.unsplash.com/photo-1498049794561-7780e7231661?w=800 | D6: Sí | E6: =IF(B6="","",COUNTIF(Productos!$C$2:$C$500,B6)) | F6: =IF(B6="","",SUMIFS(Productos!$E$2:$E$500,Productos!$C$2:$C$500,B6,Productos!$N$2:$N$500,"Disponible"))
A7: CAT006 | B7: Dulces y Botanas | C7: https://images.unsplash.com/photo-1582058091505-f87a2e55a40f?w=800 | D7: Sí | E7: =IF(B7="","",COUNTIF(Productos!$C$2:$C$500,B7)) | F7: =IF(B7="","",SUMIFS(Productos!$E$2:$E$500,Productos!$C$2:$C$500,B7,Productos!$N$2:$N$500,"Disponible"))
A8: CAT007 | B8: Accesorios | C8: https://images.unsplash.com/photo-1523293182086-7651a899d37f?w=800 | D8: Sí | E8: =IF(B8="","",COUNTIF(Productos!$C$2:$C$500,B8)) | F8: =IF(B8="","",SUMIFS(Productos!$E$2:$E$500,Productos!$C$2:$C$500,B8,Productos!$N$2:$N$500,"Disponible"))
A9: CAT008 | B9: Hogar | C9: https://images.unsplash.com/photo-1513694203232-719a280e022f?w=800 | D9: Sí | E9: =IF(B9="","",COUNTIF(Productos!$C$2:$C$500,B9)) | F9: =IF(B9="","",SUMIFS(Productos!$E$2:$E$500,Productos!$C$2:$C$500,B9,Productos!$N$2:$N$500,"Disponible"))
A10: CAT009 | B10: Bolsas y Mochilas | C10: https://images.unsplash.com/photo-1548036328-c9fa89d128fa?w=800 | D10: Sí | E10: =IF(B10="","",COUNTIF(Productos!$C$2:$C$500,B10)) | F10: =IF(B10="","",SUMIFS(Productos!$E$2:$E$500,Productos!$C$2:$C$500,B10,Productos!$N$2:$N$500,"Disponible"))
A11: CAT010 | B11: Joyería y Bisutería | C11: https://images.unsplash.com/photo-1515562141207-7a88fb7ce338?w=800 | D11: Sí | E11: =IF(B11="","",COUNTIF(Productos!$C$2:$C$500,B11)) | F11: =IF(B11="","",SUMIFS(Productos!$E$2:$E$500,Productos!$C$2:$C$500,B11,Productos!$N$2:$N$500,"Disponible"))
A12: CAT011 | B12: Juguetes | C12: https://images.unsplash.com/photo-1558060370-d644479cb6f7?w=800 | D12: Sí | E12: =IF(B12="","",COUNTIF(Productos!$C$2:$C$500,B12)) | F12: =IF(B12="","",SUMIFS(Productos!$E$2:$E$500,Productos!$C$2:$C$500,B12,Productos!$N$2:$N$500,"Disponible"))
A13: CAT012 | B13: Otros | C13: https://images.unsplash.com/photo-1472851294608-062f824d29cc?w=800 | D13: Sí | E13: =IF(B13="","",COUNTIF(Productos!$C$2:$C$500,B13)) | F13: =IF(B13="","",SUMIFS(Productos!$E$2:$E$500,Productos!$C$2:$C$500,B13,Productos!$N$2:$N$500,"Disponible"))

Sheet Inventario
A1: ID Movimiento | B1: Fecha | C1: ID Producto | D1: Nombre del Producto | E1: Tipo de Movimiento | F1: Cambio de Cantidad | G1: Cantidad Anterior | H1: Nueva Cantidad | I1: Motivo / Referencia
A2: M001 | B2: 2026-10-28 | C2: P006 | D2: =IF(C2="","",IFERROR(VLOOKUP(C2,Productos!$A$2:$B$500,2,FALSE),"Sudadera Oversize Caballero")) | E2: Entrada de Mercancía | F2: 1 | G2: 0 | H2: =IF(AND(F2="",G2=""),"",G2+F2) | I2: Ingreso inicial de lote
A3: M002 | B3: 2026-10-28 | C3: P006 | D3: =IF(C3="","",IFERROR(VLOOKUP(C3,Productos!$A$2:$B$500,2,FALSE),"Sudadera Oversize Caballero")) | E3: Venta | F3: -1 | G3: 1 | H3: =IF(AND(F3="",G3=""),"",G3+F3) | I3: Venta confirmada (PED-001)
A4: M003 | B4: 2026-10-29 | C4: P002 | D4: =IF(C4="","",IFERROR(VLOOKUP(C4,Productos!$A$2:$B$500,2,FALSE),"Chamarra Mezclilla Dama")) | E4: Entrada de Mercancía | F4: 4 | G4: 0 | H4: =IF(AND(F4="",G4=""),"",G4+F4) | I4: Nuevo lote chamarras importadas
A5: M004 | B5: 2026-10-30 | C5: P002 | D5: =IF(C5="","",IFERROR(VLOOKUP(C5,Productos!$A$2:$B$500,2,FALSE),"Chamarra Mezclilla Dama")) | E5: Venta | F5: -1 | G5: 4 | H5: =IF(AND(F5="",G5=""),"",G5+F5) | I5: Venta confirmada (PED-004)
A6: M005 | B6: 2026-10-29 | C6: P003 | D6: =IF(C6="","",IFERROR(VLOOKUP(C6,Productos!$A$2:$B$500,2,FALSE),"Set Labiales Matte Larga Duración")) | E6: Venta | F6: -2 | G6: 7 | H6: =IF(AND(F6="",G6=""),"",G6+F6) | I6: Venta confirmada (PED-002)
A7: M006 | B7: 2026-10-30 | C7: P004 | D7: =IF(C7="","",IFERROR(VLOOKUP(C7,Productos!$A$2:$B$500,2,FALSE),"Audífonos Inalámbricos Bluetooth Pro")) | E7: Apartado | F7: 0 | G7: 1 | H7: =IF(AND(F7="",G7=""),"",G7+F7) | I7: Apartado pendiente de verificación (PED-003)

Sheet Dashboard
B2: PANEL DE CONTROL — TIENDA WHATSAPP
B5: Nombre de la Tienda | C5: Mi Tienda WhatsApp
B6: Número de WhatsApp (con clave país 52) | C6: 525512345678
B7: Enlace Público de tu App | C7: https://mitienda.glide.page
B11: Total de Productos Registrados | C11: =COUNTA(Productos!A2:A500)
B12: Productos Disponibles | C12: =COUNTIF(Productos!N2:N500,"Disponible")
B13: Productos Apartados | C13: =COUNTIF(Productos!N2:N500,"Apartado")
B14: Productos Vendidos / Agotados | C14: =COUNTIF(Productos!N2:N500,"Agotado")
B15: Unidades Totales Disponibles | C15: =SUMIF(Productos!N2:N500,"Disponible",Productos!E2:E500)
B16: Valor del Inventario Disponible (MXN) | C16: =SUMPRODUCT(--(Productos!N2:N500="Disponible"),Productos!D2:D500,Productos!E2:E500)
B17: Pendientes de Publicar en Estado WhatsApp | C17: =COUNTIFS(Productos!Q2:Q500,"No",Productos!N2:N500,"Disponible")
B18: Pagos Pendientes de Revisión | C18: =COUNTIF(Pedidos!M2:M500,"Pendiente")
B19: Monto en Pagos Pendientes (MXN) | C19: =SUMIFS(Pedidos!J2:J500,Pedidos!M2:M500,"Pendiente")
B20: Ventas Cobradas / Aprobadas (MXN) | C20: =SUMIFS(Pedidos!J2:J500,Pedidos!M2:M500,"Aprobado")
B21: Total de Pedidos Registrados | C21: =COUNTA(Pedidos!A2:A500)
B22: Total de Clientes en Base de Datos | C22: =COUNTA(Clientes!A2:A500)

Sheet Usuarios
A1: ID Usuario | B1: Nombre | C1: Correo Electrónico | D1: Rol | E1: WhatsApp | F1: Activo | G1: Permisos en Glide
A2: U001 | B2: Administrador Principal | C2: admin@mitienda.com | D2: Admin | E2: 525512345678 | F2: Sí | G2: Acceso total: Agregar, editar, ocultar productos y aprobar comprobantes de pago
A3: U002 | B3: Ventas / Atención WhatsApp | C3: ventas@mitienda.com | D3: Vendedor | E3: 525587654321 | F3: Sí | G3: Acceso operativo: Registrar pedidos, apartar productos y cargar inventario
